{"type": "Feature", "id": 12515063, "geometry": {"type": "Point", "coordinates": [7.5661, 6.4756]}, "properties": {"woe:id": 12515063, "woe:parent_id": 1390643, "woe:name": "Enugu Airport", "woe:placetype": 14, "woe:placetype_name": "Airport", "woe:lang": "ENG", "iso:country": "NG", "meta:provider": ["geoplanet:7.3.1", "geoplanet:7.3.2", "geoplanet:7.4.0", "geoplanet:7.4.1", "geoplanet:7.5.1", "geoplanet:7.5.2", "geoplanet:7.6.0", "geoplanet:7.8.1", "geoplanet:7.9.0", "geoplanet:7.10.0", "geoplanet:8.0.0", "woeplanet:8.0.0"], "meta:indexed": "2020-08-20T20:29:20.079010", "woe:alias_ENG_V": ["ENU Airport", "ENU"], "meta:updated": "2020-10-14T11:25:04.941118", "woe:hierarchy": {"continent": 24865670, "country": 23424908, "town": 0, "planet": 1, "county": 56058274, "suburb": 0, "state": 2346366, "region": 0, "localadmin": 0}, "woe:timezone_id": 28350709, "woe:hash": "s1jku4v7ngm4", "woe:centroid": [7.5661, 6.4756], "geom:latitude": 6.4756, "geom:longitude": 7.5661, "geom:hash": "s1jku4v7ngm4", "woe:latitude": 6.4756, "geom:centroid": [7.5661, 6.4756], "woe:longitude": 7.5661, "woe:repo": "woeplanet-airport-ng", "geom:area": 0.0, "woe:scale": 19}}